[
    {"title": "Avengers Endgame", "type": "video/mp4"},
    {"title": "Avengers Infinity War", "type": "video/mp4"},
    {"title": "Jurassic World", "type": "video/mp4"},
    {"title": "The Hangover Part II", "type": "video/mp4"},
    {"title": "Frozen II", "type": "video/mp4"},
    {"title": "Spectre", "type": "video/mp4"},
    {"title": "Minions", "type": "video/mp4"},
    {"title": "Aquaman", "type": "video/mp4"},
    {"title": "Joker", "type": "video/mp4"},
    {"title": "Aladdin", "type": "video/mp4"}
  ]
